gandmardu/__init__.py
gandmardu/main.py
gandmardu-1.0.3.dist-info/METADATA
gandmardu-1.0.3.dist-info/WHEEL
gandmardu-1.0.3.dist-info/entry_points.txt
gandmardu-1.0.3.dist-info/top_level.txt
gandmardu-1.0.3.dist-info/RECORD
