Metadata-Version: 2.1
Name: gandmardu
Version: 1.0.3
Summary: A package to generate HelloWorldFolder with a simple Hello, World! file.
Home-page: https://github.com/yourusername/generate_task_manager
Author: Athishns
Author-email: athishnsofficial@gmail.com
Classifier: Programming Language :: Python :: 3
Classifier: License :: OSI Approved :: MIT License
Classifier: Operating System :: OS Independent
Requires-Python: >=3.6
